AUTHORS.rst
CONTRIBUTING.rst
HISTORY.rst
LICENSE
MANIFEST.in
README.rst
setup.cfg
setup.py
docs/Makefile
docs/authors.rst
docs/conf.py
docs/contributing.rst
docs/history.rst
docs/index.rst
docs/installation.rst
docs/make.bat
docs/readme.rst
docs/usage.rst
static_api/__init__.py
static_api/cli.py
static_api.egg-info/PKG-INFO
static_api.egg-info/SOURCES.txt
static_api.egg-info/dependency_links.txt
static_api.egg-info/entry_points.txt
static_api.egg-info/not-zip-safe
static_api.egg-info/requires.txt
static_api.egg-info/top_level.txt
tests/__init__.py
tests/test_static_api.py