Metadata-Version: 1.1
Name: static-api
Version: 0.0.7
Summary: A tool for generating HTTP APIs off of static files.
Home-page: https://github.com/darylyu/static-api
Author: D. Yu
Author-email: dyu@fastmail.com
License: GNU General Public License v3
Keywords: static-api
Platform: UNKNOWN
Classifier: Development Status :: 2 - Pre-Alpha
Classifier: Intended Audience :: Developers
Classifier: License :: OSI Approved :: GNU General Public License v3 (GPLv3)
Classifier: Natural Language :: English
Classifier: Programming Language :: Python :: 2
Classifier: Programming Language :: Python :: 2.6
Classifier: Programming Language :: Python :: 2.7
Classifier: Programming Language :: Python :: 3
Classifier: Programming Language :: Python :: 3.3
Classifier: Programming Language :: Python :: 3.4
Classifier: Programming Language :: Python :: 3.5
